blockmodel/__init__.py
blockmodel/constants.py
blockmodel/mapper.py
blockmodel/model.py
blockmodel/readers/__init__.py
blockmodel/readers/base.py
blockmodel/readers/json_array.py
blockmodel/readers/png.py
blockmodel/readers/png_reader.py
blockmodel/readers/schematic.py
blockmodel/readers/sparse_json.py
blockmodel/resources/blocks.csv
blockmodel/resources/player.mtl
blockmodel/resources/player.obj
blockmodel/resources/player.x3d
blockmodel/resources/printcraft.mtl
blockmodel/resources/terrain.png
blockmodel/resources/terrain_big.png
blockmodel/templates/collada.xml
blockmodel/templates/collada2.xml
blockmodel/templates/x3d_faces.xml
blockmodel/templates/x3d_triangles.xml
blockmodel/tests/__init__.py
blockmodel/tests/blockmodel_tests.py
blockmodel/tests/data/ref/block.png
blockmodel/tests/data/ref/cup2.obj
blockmodel/tests/data/ref/cup2.x3d
blockmodel/tests/data/ref/png_2_obj.obj
blockmodel/tests/data/ref/sparse_obj.obj
blockmodel/tests/data/ref/sparse_test.csv
blockmodel/tests/data/ref/x3d_ref.x3d
blockmodel/writers/__init__.py
blockmodel/writers/file_writers.py
blockmodel/writers/stl_writer.py
blockmodel-1.0.1.dist-info/DESCRIPTION.rst
blockmodel-1.0.1.dist-info/METADATA
blockmodel-1.0.1.dist-info/RECORD
blockmodel-1.0.1.dist-info/WHEEL
blockmodel-1.0.1.dist-info/metadata.json
blockmodel-1.0.1.dist-info/top_level.txt
