Metadata-Version: 2.0
Name: blockmodel
Version: 1.0.1
Summary: Converts Minecraft models to 3D models
Home-page: https://github.com/paulharter/blockmodel
Author: Paul Harter
Author-email: paul@glowinthedark.co.uk
License: MIT
Keywords: minecraft 3D printing
Platform: UNKNOWN
Classifier: Development Status :: 5 - Production/Stable
Classifier: Natural Language :: English
Classifier: Operating System :: OS Independent
Classifier: Programming Language :: Python :: 3.5
Classifier: Programming Language :: Python :: 2.7
Classifier: Intended Audience :: Education
Classifier: License :: OSI Approved :: MIT License
Requires-Dist: jinja2
Requires-Dist: nbt
